Metadata-Version: 1.0
Name: PyGsheetAPI
Version: 0.1
Summary: Python Gsheet Wrapper Library
Home-page: http://github.com/samlazrak/pygsheet-api
Author: Sam Lazrak
Author-email: samlazrak@outlook.com
License: MIT
Platform: UNKNOWN
